{"data":[{"birth_mon":3,"gender":"female","birth_day":3,"birth_year":null,"blood_type":null,"images":{"small":"https://lain.bgm.tv/r/100/pic/crt/l/b5/5c/10970_crt_lnq7l.jpg","grid":"https://lain.bgm.tv/pic/crt/g/b5/5c/10970_crt_lnq7l.jpg","large":"https://lain.bgm.tv/pic/crt/l/b5/5c/10970_crt_lnq7l.jpg","medium":"https://lain.bgm.tv/r/400/pic/crt/l/b5/5c/10970_crt_lnq7l.jpg"},"summary":"流线型的纤长美腿、发育得沉甸甸的巨大胸器引人注目的女孩子。\r\n身为学园唯一的三年级学生，作为很会照顾人的大姐姐被众人仰慕着。\r\n给人很可靠的强烈印象，对主人公也是百般关照，不过时常也会搞些孩子气的恶作剧，做出疑似天然呆的行动。\r\n\r\n因为老家经营着在东京都内设立了总店的老字号酒家的关系，对料理有着自信，家务总地来说是擅长领域。\r\n无微不至的有点H的御姐──这么说虽然有语病，但也没法断言不是。从这点也可以看出的确是个让人没法掉以轻心的存在。","name":"周防天音","infobox":[{"key":"简体中文名","value":"周防天音"},{"key":"别名","value":[{"k":"日文名","v":"周防 天音"},{"k":"纯假名","v":"すおう あまね"},{"k":"罗马字","v":"Suou Amane"}]},{"key":"性别","value":"女"},{"key":"生日","value":"3月3日"},{"key":"血型","value":"A型"},{"key":"身高","value":"169cm"},{"key":"BWH","value":"91(F)/59/88"}],"stat":{"comments":67,"collects":328},"id":10970,"locked":false,"type":1,"nsfw":false},{"birth_mon":null,"gender":"male","birth_day":null,"birth_year":null,"blood_type":null,"images":{"small":"https://lain.bgm.tv/r/100/pic/crt/l/cc/62/174100_crt_sx7zx.jpg?r=1744504477","grid":"https://lain.bgm.tv/pic/crt/g/cc/62/174100_crt_sx7zx.jpg?r=1744504477","large":"https://lain.bgm.tv/pic/crt/l/cc/62/174100_crt_sx7zx.jpg?r=1744504477","medium":"https://lain.bgm.tv/r/400/pic/crt/l/cc/62/174100_crt_sx7zx.jpg?r=1744504477"},"summary":"銀湾にて右氶相の位にある貴族。銀湾発展のため、凍玻璃を手に入れたいと考えている急進派。\r\n穏やかで上品、貴族然とした柔らかい物腰だが……","name":"周防","infobox":[{"key":"别名","value":[{"k":"罗马字","v":"Suou"}]},{"key":"性别","value":"男"}],"stat":{"comments":0,"collects":0},"id":174100,"locked":false,"type":1,"nsfw":false},{"birth_mon":null,"gender":"male","birth_day":null,"birth_year":null,"blood_type":null,"images":{"small":"https://lain.bgm.tv/r/100/pic/crt/l/f4/c6/22363_crt_ft01y.jpg","grid":"https://lain.bgm.tv/pic/crt/g/f4/c6/22363_crt_ft01y.jpg","large":"https://lain.bgm.tv/pic/crt/l/f4/c6/22363_crt_ft01y.jpg","medium":"https://lain.bgm.tv/r/400/pic/crt/l/f4/c6/22363_crt_ft01y.jpg"},"summary":"","name":"スオウ","infobox":[{"key":"简体中文名","value":"周防"},{"key":"别名","value":[]},{"key":"性别","value":"男"}],"stat":{"comments":0,"collects":8},"id":22363,"locked":false,"type":1,"nsfw":false},{"birth_mon":7,"gender":"female","birth_day":26,"birth_year":null,"blood_type":4,"images":{"small":"https://lain.bgm.tv/r/100/pic/crt/l/03/9d/2015_crt_UYDGp.jpg","grid":"https://lain.bgm.tv/pic/crt/g/03/9d/2015_crt_UYDGp.jpg","large":"https://lain.bgm.tv/pic/crt/l/03/9d/2015_crt_UYDGp.jpg","medium":"https://lain.bgm.tv/r/400/pic/crt/l/03/9d/2015_crt_UYDGp.jpg"},"summary":"喜好各种体育活动，学习成绩也不错，除了对美术特别苦手。不擅长绑缎带。与花井是青梅竹马。曾一直崇拜和单恋比自己大两届的私人教师神津正弘，希望能努力学习考进对方现所在的大学，直到发现对方在大学里已经交了女友后，虽然悲伤但很快又重新振作起来。对播磨拳儿颇有欣赏和同情，因此逐渐想撮合他和爱理之间的关系，跟班中的麻生发展中，已经分手了。","name":"周防美琴","infobox":[{"key":"简体中文名","value":"周防美琴"},{"key":"别名","value":[{"k":"日文名","v":"周防美琴"},{"k":"罗马字","v":"Suou Mikoto"}]},{"key":"性别","value":"女"},{"key":"生日","value":"7月26日"},{"key":"血型","value":"O"},{"key":"身高","value":"170cm"},{"key":"引用来源","value":"anidb.net"}],"stat":{"comments":18,"collects":39},"id":2015,"locked":false,"type":1,"nsfw":false},{"birth_mon":8,"gender":"female","birth_day":26,"birth_year":null,"blood_type":4,"images":{"small":"https://lain.bgm.tv/r/100/pic/crt/l/d9/35/4321_crt_anidb.jpg","grid":"https://lain.bgm.tv/pic/crt/g/d9/35/4321_crt_anidb.jpg","large":"https://lain.bgm.tv/pic/crt/l/d9/35/4321_crt_anidb.jpg","medium":"https://lain.bgm.tv/r/400/pic/crt/l/d9/35/4321_crt_anidb.jpg"},"summary":"","name":"周防院奏","infobox":[{"key":"简体中文名","value":"周防院奏"},{"key":"别名","value":[{"k":"日文名","v":"周防院 奏"},{"k":"纯假名","v":"すおういん かな"},{"k":"罗马字","v":"Suouin Kana"}]},{"key":"性别","value":"女"},{"key":"生日","value":"8月26日"},{"key":"血型","value":"O"},{"key":"身高","value":"140cm"}],"stat":{"comments":5,"collects":17},"id":4321,"locked":false,"type":1,"nsfw":false},{"birth_mon":null,"gender":"female","birth_day":null,"birth_year":null,"blood_type":null,"images":{"small":"https://lain.bgm.tv/r/100/pic/crt/l/7e/e9/12728_crt_W7Xi0.jpg","grid":"https://lain.bgm.tv/pic/crt/g/7e/e9/12728_crt_W7Xi0.jpg","large":"https://lain.bgm.tv/pic/crt/l/7e/e9/12728_crt_W7Xi0.jpg","medium":"https://lain.bgm.tv/r/400/pic/crt/l/7e/e9/12728_crt_W7Xi0.jpg"},"summary":"　　年长一岁的前辈。世界第一的周防集团的独生女。\r\n　　别说是学园甚至是全县没有一个不知道她的名字的有名的大小姐。\r\n　　作为真正的大小姐的美鶴待人温和，并不炫耀自己的出身。\r\n　　但或许太过深居闺出，对一般常识和世间的事相当一知半解。\r\n　　虽然没有恶意，但她天然呆的言行经常是周围无语。\r\n\r\n　　【在爷爷还没来之前，我们两个人先走吧】","name":"周防美鶴","infobox":[{"key":"简体中文名","value":"周防美鹤"},{"key":"别名","value":[{"k":"日文名","v":"周防美鶴"},{"k":"纯假名","v":"Suou Mitsuru"}]},{"key":"性别","value":"女"},{"key":"身高","value":"158cm"},{"key":"BWH","value":"B88/ W55/ H85"},{"key":"班级","value":"私立愛宕学園2年C組"}],"stat":{"comments":1,"collects":6},"id":12728,"locked":false,"type":1,"nsfw":false},{"birth_mon":null,"gender":"male","birth_day":null,"birth_year":null,"blood_type":null,"images":{"small":"https://lain.bgm.tv/r/100/pic/crt/l/de/dc/13425_crt_0d11S.jpg?r=1570552091","grid":"https://lain.bgm.tv/pic/crt/g/de/dc/13425_crt_0d11S.jpg?r=1570552091","large":"https://lain.bgm.tv/pic/crt/l/de/dc/13425_crt_0d11S.jpg?r=1570552091","medium":"https://lain.bgm.tv/r/400/pic/crt/l/de/dc/13425_crt_0d11S.jpg?r=1570552091"},"summary":"現名人。大学からかるたを始めて3年で名人になり、9巻で名人戦4連覇に成功した。\r\n    大学は留年中。声が凄く小さい。また和菓子が好き。\r\n    聴力が非常に優れており、彼にとっての一字決まりの札は28枚だという。\r\n    その圧倒的な強さから名人戦以外の試合に飽きており、かるた会にもかなり非協力的。\r\n    若宮詩暢にだけは対戦してみたいという執着を持っている。","name":"周防久志","infobox":[{"key":"简体中文名","value":"周防久志"},{"key":"别名","value":[{"k":"日文名","v":"周防 久志"},{"k":"纯假名","v":"すおう ひさし"},{"k":"罗马字","v":"Suou Hisashi"}]},{"key":"性别","value":"男"},{"key":"引用来源","value":"Wiki(jp)"}],"stat":{"comments":3,"collects":5},"id":13425,"locked":false,"type":1,"nsfw":false},{"birth_mon":8,"gender":"male","birth_day":13,"birth_year":null,"blood_type":2,"images":{"small":"https://lain.bgm.tv/r/100/pic/crt/l/b1/b1/15935_crt_oc4sA.jpg?r=1427919339","grid":"https://lain.bgm.tv/pic/crt/g/b1/b1/15935_crt_oc4sA.jpg?r=1427919339","large":"https://lain.bgm.tv/pic/crt/l/b1/b1/15935_crt_oc4sA.jpg?r=1427919339","medium":"https://lain.bgm.tv/r/400/pic/crt/l/b1/b1/15935_crt_oc4sA.jpg?r=1427919339"},"summary":"","name":"周防尊","infobox":[{"key":"简体中文名","value":"周防尊"},{"key":"别名","value":[{"k":"纯假名","v":"すおう みこと"},{"k":"罗马字","v":"Suoh Mikoto"}]},{"key":"性别","value":"男"},{"key":"生日","value":"8月13日"},{"key":"血型","value":"B"},{"key":"身高","value":"185cm"}],"stat":{"comments":8,"collects":103},"id":15935,"locked":false,"type":1,"nsfw":false},{"birth_mon":null,"gender":"male","birth_day":null,"birth_year":null,"blood_type":null,"images":{"small":"https://lain.bgm.tv/r/100/pic/crt/l/49/64/17015_crt_YZ60e.jpg","grid":"https://lain.bgm.tv/pic/crt/g/49/64/17015_crt_YZ60e.jpg","large":"https://lain.bgm.tv/pic/crt/l/49/64/17015_crt_YZ60e.jpg","medium":"https://lain.bgm.tv/r/400/pic/crt/l/49/64/17015_crt_YZ60e.jpg"},"summary":"七姉妹学園3-Bの生徒。18歳。オイルライターを常に持ち歩いており、蓋を鳴らして遊ぶ癖がある。ルックスの良さとクールな立ち居振る舞いから、女子生徒の人気は高い。他人との馴れ合うことを嫌って一人で行動することが多いが、本来は仲間思いの優しい性格をしている。趣味はバイクいじりとものまね（声帯模写）。『罪』では主人公、『罰』では物語の鍵を握る準主人公として活躍する。 \r\n使用武器は剣。初期ペルソナは「SUN ヴォルカヌス」（罪）、「SUN アポロ」（罰）。 \r\n\r\n\r\n罪 \r\nふとしたきっかけで栄吉、リサと共にジョーカーに狙われることになり、ジョーカーに関連する事件を追ってゆくことになる。寡黙だが、メンバーを力強く引っ張る頼れるリーダーだった。 \r\n10年前のある縁日に淳・リサ・栄吉と出会い、全員がフェザーマンのお面を着けていたことで「仮面党」を名乗って遊ぶようになる。そこに「お姉ちゃん」が加わるも、とある事件がきっかけで全員バラバラとなってしまった。この時、一時的にペルソナ能力に目覚める。 \r\n罰 \r\nJOKERやペルソナにまつわる珠閒瑠市の事件を調査し、単独で追っている。事件を追い始めるまでは、『罪』以上に不良じみた少年で、家出と不登校を繰り返していた。吉栄杏奈と仲が良く、よくクラブで遊んでいたらしい。その性格には、父親の汚職による退職と家庭問題が影響しているとも言われる。 \r\nデータ継承することで、罪の能力をアポロの熟練度以外すべてを引き継げる。リメイク版では舞耶と合流する以前のストーリーを見ることができる。ニャルラトホテプの因果に魅入られたものの証として、腕に纏わりつくような痣が存在しており、アディショナルシナリオによると、この痣は時々締め付けるような痛みを発するらしい。 \r\n栄吉・リサ・淳とは違い、かつて克哉と「ペルソナ様」をしていたため、『罰』世界でもペルソナが使える。 \r\n物語開始以前の達哉は父を「親父」、克哉を「兄貴」、杏奈を「杏奈」と呼んでいたが、現在はそれぞれ「父さん」「兄さん」「吉栄」と呼んでいる。","name":"周防達哉","infobox":[{"key":"别名","value":[]},{"key":"性别","value":"男"}],"stat":{"comments":3,"collects":23},"id":17015,"locked":false,"type":1,"nsfw":false},{"birth_mon":null,"gender":"male","birth_day":null,"birth_year":null,"blood_type":null,"images":{"small":"https://lain.bgm.tv/r/100/pic/crt/l/21/9e/17022_crt_Dr3pa.jpg","grid":"https://lain.bgm.tv/pic/crt/g/21/9e/17022_crt_Dr3pa.jpg","large":"https://lain.bgm.tv/pic/crt/l/21/9e/17022_crt_Dr3pa.jpg","medium":"https://lain.bgm.tv/r/400/pic/crt/l/21/9e/17022_crt_Dr3pa.jpg"},"summary":"周防達哉の兄で、港南警察署刑事課に所属する若き刑事。階級は巡査部長。汚職の罪を着せられ警察を退職した父の冤罪・汚名を晴らすため、自ら夢を捨てて警察官となった。生真面目な性格で口うるさいが、家族に対する愛情は強い。達哉の名前を変更した場合は、それに合わせて苗字が変わる。 \r\n罪 \r\nサブキャラクターとして登場。素行の良くない達哉に対して辛辣な言葉を浴びせているが、一方で指名手配中の達哉を見て見ぬふりで見逃したり、達哉らが正義の味方だという噂が流れるとそれを密かに喜んだりしていたという話をゲーム中に聞く事ができる。 \r\n罰 \r\nJOKERによる連続殺人事件の捜査から外され、舞耶らと共に独自に事件を追うようになる。猫好きだが猫アレルギーで、好物は甘いものとカレーライス、苦手な食べ物は辛い物。少年時代はパティシエに憧れており、現在でもお菓子作りを趣味にしている。当初、舞耶の言うデジャヴュの少年が達哉である事を知らなかったが、空の科学館で対面したことで判明する。 \r\n家庭問題を抱えていることもあり、達哉に対しては辛辣な態度を取る一方、やや過保護な様子を見せる。人型戦車「X-2」に乗り込んでいる達哉に対して免許の心配をするなど、ずれた発言をすることがある。 \r\n使用武器は拳銃。初期ペルソナは「JUSTICE ヘリオス」。","name":"周防克哉","infobox":[{"key":"简体中文名","value":"周防克哉"},{"key":"别名","value":[]},{"key":"性别","value":"男"}],"stat":{"comments":2,"collects":10},"id":17022,"locked":false,"type":1,"nsfw":false}],"total":229,"limit":10,"offset":0}
