{"birth_mon":null,"gender":"male","birth_day":null,"birth_year":null,"blood_type":null,"images":{"small":"https://lain.bgm.tv/r/100/pic/crt/l/48/9c/56787_crt_33391.jpg","grid":"https://lain.bgm.tv/pic/crt/g/48/9c/56787_crt_33391.jpg","large":"https://lain.bgm.tv/pic/crt/l/48/9c/56787_crt_33391.jpg","medium":"https://lain.bgm.tv/r/400/pic/crt/l/48/9c/56787_crt_33391.jpg"},"summary":"国連軍横浜基地の司令官。「オルタネイティヴ4」の終了、「オルタネイティヴ5」の発動を伝えに来る。\r\nインドの出身で、階級は准将。かつてインド亜大陸の激戦を潜り抜けた猛将でもある。\r\n『桜花作戦』開始直前に実施した演説では「諸君ら若者を過酷な戦場に送り出さなければならない、戦う術しか教えられなかった我々を許すな」と語った。","name":"パウル・ラダビノッド","infobox":[{"key":"简体中文名","value":"鲍尔·拉达比诺德"},{"key":"别名","value":[]},{"key":"性别","value":"男"},{"key":"引用来源","value":"Wikipedia"}],"stat":{"comments":3,"collects":6},"id":56787,"locked":false,"type":1,"nsfw":false}
