{"birth_mon":null,"gender":"female","birth_day":null,"birth_year":null,"blood_type":null,"images":{"small":"https://lain.bgm.tv/r/100/pic/crt/l/81/d5/29015_crt_S1ikM.jpg?r=1421162363","grid":"https://lain.bgm.tv/pic/crt/g/81/d5/29015_crt_S1ikM.jpg?r=1421162363","large":"https://lain.bgm.tv/pic/crt/l/81/d5/29015_crt_S1ikM.jpg?r=1421162363","medium":"https://lain.bgm.tv/r/400/pic/crt/l/81/d5/29015_crt_S1ikM.jpg?r=1421162363"},"summary":"米国軍所属のフィンランド人。\r\n米軍対日派遣部隊の衛士。\r\n階級は少尉。\r\n人当たりが良く家族想い。","name":"イルマ・テスレフ","infobox":[{"key":"简体中文名","value":"伊露玛·塔斯雷夫"},{"key":"别名","value":[]},{"key":"性别","value":"女"}],"stat":{"comments":2,"collects":2},"id":29015,"locked":false,"type":1,"nsfw":false}
